{
    "info": {
        "name": "Player Detection",
        "description": "Detect players by role (pitcher, batter, catcher)",
        "type": "detection",
        "date_created": "2024-10-27T14:42:53.769849"
    },
    "categories": [
        {
            "id": 1,
            "name": "pitcher",
            "color": "#FF6B6B"
        },
        {
            "id": 2,
            "name": "batter",
            "color": "#4ECDC4"
        },
        {
            "id": 3,
            "name": "catcher",
            "color": "#45B7D1"
        }
    ],
    "images": [],
    "annotations": []
}